{
  "$id": "adjustMultiplier",
  "name": "adjustMultiplier",
  "runtime": "node-18.0",
  "execute": ["users"],
  "events": [],
  "schedule": "0 1 * * *",
  "timeout": 300,
  "enabled": true,
  "logging": true,
  "entrypoint": "src/main.js",
  "commands": "npm install",
  "path": "functions/adjustMultiplier",
  "vars": {
    "APPWRITE_ENDPOINT": "",
    "APPWRITE_PROJECT_ID": "",
    "APPWRITE_API_KEY": "",
    "APPWRITE_DATABASE_ID": "builder_circle",
    "PARTICIPATION_COLLECTION_ID": "cycle_participation",
    "MULTIPLIERS_COLLECTION_ID": "multipliers",
    "LEDGER_COLLECTION_ID": "ownership_ledger",
    "CYCLES_COLLECTION_ID": "build_cycles"
  }
}
